runchain/__init__.py
runchain/__main__.py
runchain/chain.py
runchain/commands.py
runchain/exceptions.py
runchain-0.2.1.dist-info/licenses/LICENSE
runchain-0.2.1.dist-info/METADATA
runchain-0.2.1.dist-info/WHEEL
runchain-0.2.1.dist-info/entry_points.txt
runchain-0.2.1.dist-info/top_level.txt
runchain-0.2.1.dist-info/RECORD
