Metadata-Version: 2.4
Name: runchain
Version: 0.2.1
Summary: A tool for running command chains
Author-email: Richard Terry <code@radiac.net>
License-Expression: BSD-3-Clause
Project-URL: Homepage, https://radiac.net/projects/runchain/
Project-URL: Documentation, https://github.com/radiac/runchain
Project-URL: Changelog, https://runchain.readthedocs.io/en/latest/changelog.html
Project-URL: Repository, https://github.com/radiac/runchain
Project-URL: Issues, https://github.com/radiac/runchain/issues
Classifier: Development Status :: 4 - Beta
Classifier: Programming Language :: Python :: 3
Classifier: Operating System :: OS Independent
Requires-Python: >=3.9
License-File: LICENSE
Requires-Dist: click
Requires-Dist: crondir
Dynamic: license-file
